untouched/__init__.py
untouched/builder.py
untouched/builder.pyi
untouched/py.typed
untouched/registry.py
untouched/registry.pyi
untouched-0.2.7.dist-info/METADATA
untouched-0.2.7.dist-info/WHEEL
untouched-0.2.7.dist-info/RECORD
