Metadata-Version: 2.1
Name: untouched
Version: 0.2.7
Summary: Immutable builder, carbon copy of lann/builder package in GoLang.
Author: damacaner
Author-email: caner@damacana.dev
Requires-Python: >=3.11,<4.0
Classifier: Programming Language :: Python :: 3
Classifier: Programming Language :: Python :: 3.11
